[{"title":"Farmers Queries in Kisan Call Centre (KCC) from VIRUDHUNAGAR district of TAMIL NADU for the month of November 2014","url":"https://data.gov.in/node/4790921/datastore/export/csv"},{"title":"Farmers Queries in Kisan Call Centre (KCC) from ARIYALUR district of TAMIL NADU for the month of November 2014","url":"https://data.gov.in/node/4794041/datastore/export/csv"},{"title":"Farmers Queries in Kisan Call Centre (KCC) from KRISHNAGIRI district of TAMIL NADU for the month of November 2014","url":"https://data.gov.in/node/4794281/datastore/export/csv"},{"title":"Farmers Queries in Kisan Call Centre (KCC) from DHARMAPURI district of TAMIL NADU for the month of November 2014","url":"https://data.gov.in/node/4788041/datastore/export/csv"},{"title":"Farmers Queries in Kisan Call Centre (KCC) from THENI district of TAMIL NADU for the month of November 2014","url":"https://data.gov.in/node/4792601/datastore/export/csv"},{"title":"Farmers Queries in Kisan Call Centre (KCC) from NAGAPATTINAM district of TAMIL NADU for the month of November 2014","url":"https://data.gov.in/node/4792841/datastore/export/csv"},{"title":"Farmers Queries in Kisan Call Centre (KCC) from TIRUPUR district of TAMIL NADU for the month of November 2014","url":"https://data.gov.in/node/4794521/datastore/export/csv"},{"title":"Farmers Queries in Kisan Call Centre (KCC) from WEST TRIPURA district of TRIPURA for the month of November 2014","url":"https://data.gov.in/node/4794761/datastore/export/csv"},{"title":"Farmers Queries in Kisan Call Centre (KCC) from THOOTHUKUDI district of TAMIL NADU for the month of November 2014","url":"https://data.gov.in/node/4793561/datastore/export/csv"},{"title":"Farmers Queries in Kisan Call Centre (KCC) from SIVAGANGA district of TAMIL NADU for the month of November 2014","url":"https://data.gov.in/node/4793081/datastore/export/csv"},{"title":"Farmers Queries in Kisan Call Centre (KCC) from TIRUVANNAMALAI district of TAMIL NADU for the month of November 2014","url":"https://data.gov.in/node/4793321/datastore/export/csv"},{"title":"Farmers Queries in Kisan Call Centre (KCC) from CHENNAI(MADRAS) district of TAMIL NADU for the month of November 2014","url":"https://data.gov.in/node/4793801/datastore/export/csv"},{"title":"Farmers Queries in Kisan Call Centre (KCC) from TIRUPUR district of TAMIL NADU for the month of November 2014","url":"https://data.gov.in/node/4794521/datastore/export/csv"},{"title":"Farmers Queries in Kisan Call Centre (KCC) from WEST TRIPURA district of TRIPURA for the month of November 2014","url":"https://data.gov.in/node/4794761/datastore/export/csv"},{"title":"Farmers Queries in Kisan Call Centre (KCC) from THOOTHUKUDI district of TAMIL NADU for the month of November 2014","url":"https://data.gov.in/node/4793561/datastore/export/csv"},{"title":"Farmers Queries in Kisan Call Centre (KCC) from SIVAGANGA district of TAMIL NADU for the month of November 2014","url":"https://data.gov.in/node/4793081/datastore/export/csv"},{"title":"Farmers Queries in Kisan Call Centre (KCC) from TIRUVANNAMALAI district of TAMIL NADU for the month of November 2014","url":"https://data.gov.in/node/4793321/datastore/export/csv"},{"title":"Farmers Queries in Kisan Call Centre (KCC) from CHENNAI(MADRAS) district of TAMIL NADU for the month of November 2014","url":"https://data.gov.in/node/4793801/datastore/export/csv"},{"title":"Farmers Queries in Kisan Call Centre (KCC) from BADAUN district of UTTAR PRADESH for the month of November 2014","url":"https://data.gov.in/node/4798401/datastore/export/csv"},{"title":"Farmers Queries in Kisan Call Centre (KCC) from SHAHJAHANPUR district of UTTAR PRADESH for the month of November 2014","url":"https://data.gov.in/node/4798641/datastore/export/csv"},{"title":"Farmers Queries in Kisan Call Centre (KCC) from PILIBHIT district of UTTAR PRADESH for the month of November 2014","url":"https://data.gov.in/node/4798881/datastore/export/csv"},{"title":"Farmers Queries in Kisan Call Centre (KCC) from NAMAKKAL district of TAMIL NADU for the month of November 2014","url":"https://data.gov.in/node/4791161/datastore/export/csv"},{"title":"Farmers Queries in Kisan Call Centre (KCC) from KARUR district of TAMIL NADU for the month of November 2014","url":"https://data.gov.in/node/4791401/datastore/export/csv"},{"title":"Farmers Queries in Kisan Call Centre (KCC) from PERAMBALUR district of TAMIL NADU for the month of November 2014","url":"https://data.gov.in/node/4791641/datastore/export/csv"},{"title":"Farmers Queries in Kisan Call Centre (KCC) from BADAUN district of UTTAR PRADESH for the month of November 2014","url":"https://data.gov.in/node/4798401/datastore/export/csv"},{"title":"Farmers Queries in Kisan Call Centre (KCC) from SHAHJAHANPUR district of UTTAR PRADESH for the month of November 2014","url":"https://data.gov.in/node/4798641/datastore/export/csv"},{"title":"Farmers Queries in Kisan Call Centre (KCC) from PILIBHIT district of UTTAR PRADESH for the month of November 2014","url":"https://data.gov.in/node/4798881/datastore/export/csv"},{"title":"Farmers Queries in Kisan Call Centre (KCC) from NAMAKKAL district of TAMIL NADU for the month of November 2014","url":"https://data.gov.in/node/4791161/datastore/export/csv"},{"title":"Farmers Queries in Kisan Call Centre (KCC) from KARUR district of TAMIL NADU for the month of November 2014","url":"https://data.gov.in/node/4791401/datastore/export/csv"},{"title":"Farmers Queries in Kisan Call Centre (KCC) from PERAMBALUR district of TAMIL NADU for the month of November 2014","url":"https://data.gov.in/node/4791641/datastore/export/csv"},{"title":"Farmers Queries in Kisan Call Centre (KCC) from SHAHJAHANPUR district of UTTAR PRADESH for the month of November 2014","url":"https://data.gov.in/node/4798641/datastore/export/csv"},{"title":"Farmers Queries in Kisan Call Centre (KCC) from PILIBHIT district of UTTAR PRADESH for the month of November 2014","url":"https://data.gov.in/node/4798881/datastore/export/csv"},{"title":"Farmers Queries in Kisan Call Centre (KCC) from MAINPURI district of UTTAR PRADESH for the month of November 2014","url":"https://data.gov.in/node/4797681/datastore/export/csv"},{"title":"Farmers Queries in Kisan Call Centre (KCC) from KARUR district of TAMIL NADU for the month of November 2014","url":"https://data.gov.in/node/4791401/datastore/export/csv"},{"title":"Farmers Queries in Kisan Call Centre (KCC) from PERAMBALUR district of TAMIL NADU for the month of November 2014","url":"https://data.gov.in/node/4791641/datastore/export/csv"},{"title":"Farmers Queries in Kisan Call Centre (KCC) from MEERUT district of UTTAR PRADESH for the month of November 2014","url":"https://data.gov.in/node/4796241/datastore/export/csv"},{"title":"Farmers Queries in Kisan Call Centre (KCC) from AGRA district of UTTAR PRADESH for the month of November 2014","url":"https://data.gov.in/node/4797441/datastore/export/csv"},{"title":"Farmers Queries in Kisan Call Centre (KCC) from MAINPURI district of UTTAR PRADESH for the month of November 2014","url":"https://data.gov.in/node/4797681/datastore/export/csv"},{"title":"Farmers Queries in Kisan Call Centre (KCC) from ETAH district of UTTAR PRADESH for the month of November 2014","url":"https://data.gov.in/node/4797921/datastore/export/csv"},{"title":"Farmers Queries in Kisan Call Centre (KCC) from MUZAFFARNAGAR district of UTTAR PRADESH for the month of November 2014","url":"https://data.gov.in/node/4795981/datastore/export/csv"},{"title":"Farmers Queries in Kisan Call Centre (KCC) from MEERUT district of UTTAR PRADESH for the month of November 2014","url":"https://data.gov.in/node/4796241/datastore/export/csv"},{"title":"Farmers Queries in Kisan Call Centre (KCC) from GHAZIABAD district of UTTAR PRADESH for the month of November 2014","url":"https://data.gov.in/node/4796481/datastore/export/csv"},{"title":"Farmers Queries in Kisan Call Centre (KCC) from BAREILLY district of UTTAR PRADESH for the month of November 2014","url":"https://data.gov.in/node/4798161/datastore/export/csv"},{"title":"Farmers Queries in Kisan Call Centre (KCC) from JHANSI district of UTTAR PRADESH for the month of November 2014","url":"https://data.gov.in/node/4801321/datastore/export/csv"},{"title":"Farmers Queries in Kisan Call Centre (KCC) from GHAZIPUR district of UTTAR PRADESH for the month of November 2014","url":"https://data.gov.in/node/4803001/datastore/export/csv"},{"title":"Farmers Queries in Kisan Call Centre (KCC) from BULANDSHAHAR district of UTTAR PRADESH for the month of November 2014","url":"https://data.gov.in/node/4796721/datastore/export/csv"},{"title":"Farmers Queries in Kisan Call Centre (KCC) from NORTH TRIPURA district of TRIPURA for the month of November 2014","url":"https://data.gov.in/node/4795501/datastore/export/csv"},{"title":"Farmers Queries in Kisan Call Centre (KCC) from SAHARANPUR district of UTTAR PRADESH for the month of November 2014","url":"https://data.gov.in/node/4795741/datastore/export/csv"},{"title":"Farmers Queries in Kisan Call Centre (KCC) from HAMIRPUR district of UTTAR PRADESH for the month of November 2014","url":"https://data.gov.in/node/4801801/datastore/export/csv"},{"title":"Farmers Queries in Kisan Call Centre (KCC) from VARANASI district of UTTAR PRADESH for the month of November 2014","url":"https://data.gov.in/node/4802281/datastore/export/csv"},{"title":"Farmers Queries in Kisan Call Centre (KCC) from DHALAI district of TRIPURA for the month of November 2014","url":"https://data.gov.in/node/4795261/datastore/export/csv"},{"title":"Farmers Queries in Kisan Call Centre (KCC) from BANDA district of UTTAR PRADESH for the month of November 2014","url":"https://data.gov.in/node/4802041/datastore/export/csv"},{"title":"Farmers Queries in Kisan Call Centre (KCC) from MIRZAPUR district of UTTAR PRADESH for the month of November 2014","url":"https://data.gov.in/node/4802521/datastore/export/csv"},{"title":"Farmers Queries in Kisan Call Centre (KCC) from JAUNPUR district of UTTAR PRADESH for the month of November 2014","url":"https://data.gov.in/node/4802761/datastore/export/csv"},{"title":"Farmers Queries in Kisan Call Centre (KCC) from BARABANKI district of UTTAR PRADESH for the month of November 2014","url":"https://data.gov.in/node/4807081/datastore/export/csv"},{"title":"Farmers Queries in Kisan Call Centre (KCC) from JALAUN district of UTTAR PRADESH for the month of November 2014","url":"https://data.gov.in/node/4801561/datastore/export/csv"},{"title":"Farmers Queries in Kisan Call Centre (KCC) from KANPUR CITY district of UTTAR PRADESH for the month of November 2014","url":"https://data.gov.in/node/4800361/datastore/export/csv"},{"title":"Farmers Queries in Kisan Call Centre (KCC) from FARRUKHABAD district of UTTAR PRADESH for the month of November 2014","url":"https://data.gov.in/node/4799881/datastore/export/csv"},{"title":"Farmers Queries in Kisan Call Centre (KCC) from ETAWAH district of UTTAR PRADESH for the month of November 2014","url":"https://data.gov.in/node/4800121/datastore/export/csv"},{"title":"Farmers Queries in Kisan Call Centre (KCC) from FATEHPUR district of UTTAR PRADESH for the month of November 2014","url":"https://data.gov.in/node/4800601/datastore/export/csv"},{"title":"Farmers Queries in Kisan Call Centre (KCC) from JALAUN district of UTTAR PRADESH for the month of November 2014","url":"https://data.gov.in/node/4801561/datastore/export/csv"},{"title":"Farmers Queries in Kisan Call Centre (KCC) from KANPUR CITY district of UTTAR PRADESH for the month of November 2014","url":"https://data.gov.in/node/4800361/datastore/export/csv"},{"title":"Farmers Queries in Kisan Call Centre (KCC) from SULTANPUR district of UTTAR PRADESH for the month of November 2014","url":"https://data.gov.in/node/4806601/datastore/export/csv"},{"title":"Farmers Queries in Kisan Call Centre (KCC) from ETAWAH district of UTTAR PRADESH for the month of November 2014","url":"https://data.gov.in/node/4800121/datastore/export/csv"},{"title":"Farmers Queries in Kisan Call Centre (KCC) from FATEHPUR district of UTTAR PRADESH for the month of November 2014","url":"https://data.gov.in/node/4800601/datastore/export/csv"},{"title":"Farmers Queries in Kisan Call Centre (KCC) from SITAPUR district of UTTAR PRADESH for the month of November 2014","url":"https://data.gov.in/node/4805161/datastore/export/csv"},{"title":"Farmers Queries in Kisan Call Centre (KCC) from UNNAO district of UTTAR PRADESH for the month of November 2014","url":"https://data.gov.in/node/4804681/datastore/export/csv"},{"title":"Farmers Queries in Kisan Call Centre (KCC) from RAEBARELI district of UTTAR PRADESH for the month of November 2014","url":"https://data.gov.in/node/4804921/datastore/export/csv"},{"title":"Farmers Queries in Kisan Call Centre (KCC) from SITAPUR district of UTTAR PRADESH for the month of November 2014","url":"https://data.gov.in/node/4805161/datastore/export/csv"},{"title":"Farmers Queries in Kisan Call Centre (KCC) from BAHRAICH district of UTTAR PRADESH for the month of November 2014","url":"https://data.gov.in/node/4806361/datastore/export/csv"},{"title":"Farmers Queries in Kisan Call Centre (KCC) from SULTANPUR district of UTTAR PRADESH for the month of November 2014","url":"https://data.gov.in/node/4806601/datastore/export/csv"},{"title":"Farmers Queries in Kisan Call Centre (KCC) from PRATAPGARH district of UTTAR PRADESH for the month of November 2014","url":"https://data.gov.in/node/4806841/datastore/export/csv"},{"title":"Farmers Queries in Kisan Call Centre (KCC) from SULTANPUR district of UTTAR PRADESH for the month of November 2014","url":"https://data.gov.in/node/4806601/datastore/export/csv"},{"title":"Farmers Queries in Kisan Call Centre (KCC) from BASTI district of UTTAR PRADESH for the month of November 2014","url":"https://data.gov.in/node/4803961/datastore/export/csv"},{"title":"Farmers Queries in Kisan Call Centre (KCC) from MAU district of UTTAR PRADESH for the month of November 2014","url":"https://data.gov.in/node/4810441/datastore/export/csv"},{"title":"Farmers Queries in Kisan Call Centre (KCC) from SITAPUR district of UTTAR PRADESH for the month of November 2014","url":"https://data.gov.in/node/4805161/datastore/export/csv"},{"title":"Farmers Queries in Kisan Call Centre (KCC) from AZAMGARH district of UTTAR PRADESH for the month of November 2014","url":"https://data.gov.in/node/4804201/datastore/export/csv"},{"title":"Farmers Queries in Kisan Call Centre (KCC) from LUCKNOW district of UTTAR PRADESH for the month of November 2014","url":"https://data.gov.in/node/4804441/datastore/export/csv"},{"title":"Farmers Queries in Kisan Call Centre (KCC) from MAHARAHGANJ district of UTTAR PRADESH for the month of November 2014","url":"https://data.gov.in/node/4810681/datastore/export/csv"},{"title":"Farmers Queries in Kisan Call Centre (KCC) from BALLIA district of UTTAR PRADESH for the month of November 2014","url":"https://data.gov.in/node/4803241/datastore/export/csv"},{"title":"Farmers Queries in Kisan Call Centre (KCC) from GORAKHPUR district of UTTAR PRADESH for the month of November 2014","url":"https://data.gov.in/node/4803481/datastore/export/csv"},{"title":"Farmers Queries in Kisan Call Centre (KCC) from KUSHI NAGAR district of UTTAR PRADESH for the month of November 2014","url":"https://data.gov.in/node/4810921/datastore/export/csv"},{"title":"Farmers Queries in Kisan Call Centre (KCC) from SIDDHARTH NAGAR district of UTTAR PRADESH for the month of November 2014","url":"https://data.gov.in/node/4811161/datastore/export/csv"},{"title":"Farmers Queries in Kisan Call Centre (KCC) from DEORIA district of UTTAR PRADESH for the month of November 2014","url":"https://data.gov.in/node/4803721/datastore/export/csv"},{"title":"Farmers Queries in Kisan Call Centre (KCC) from SANT RAVIDAS NAGAR BHADOHI district of UTTAR PRADESH for the month of November 2014","url":"https://data.gov.in/node/4810201/datastore/export/csv"},{"title":"Farmers Queries in Kisan Call Centre (KCC) from KAUSHAMBI district of UTTAR PRADESH for the month of November 2014","url":"https://data.gov.in/node/4809001/datastore/export/csv"},{"title":"Farmers Queries in Kisan Call Centre (KCC) from CHITRAKOOT district of UTTAR PRADESH for the month of November 2014","url":"https://data.gov.in/node/4809481/datastore/export/csv"},{"title":"Farmers Queries in Kisan Call Centre (KCC) from AURAIYA district of UTTAR PRADESH for the month of November 2014","url":"https://data.gov.in/node/4808761/datastore/export/csv"},{"title":"Farmers Queries in Kisan Call Centre (KCC) from MAHOBA district of UTTAR PRADESH for the month of November 2014","url":"https://data.gov.in/node/4809241/datastore/export/csv"},{"title":"Farmers Queries in Kisan Call Centre (KCC) from FIROZABAD district of UTTAR PRADESH for the month of November 2014","url":"https://data.gov.in/node/4808041/datastore/export/csv"}]